pycarmat/__init__.py
pycarmat/__main__.py
pycarmat/gui.py
pycarmat/GUI/__init__.py
pycarmat/GUI/epsilon/__init__.py
pycarmat/GUI/epsilon/__main__.py
pycarmat/GUI/epsilon/dialog.py
pycarmat/GUI/epsilon/gui_optim.py
pycarmat/GUI/epsilon/worker.py
pycarmat/GUI/meas/README.md
pycarmat/GUI/meas/__init__.py
pycarmat/GUI/meas/__main__.py
pycarmat/GUI/meas/gui_meas.py
pycarmat/GUI/meas/classes/PermittivityEstimation.py
pycarmat/GUI/meas/classes/__init__.py
pycarmat/GUI/meas/gui/__init__.py
pycarmat/GUI/meas/gui/axes_settings_gui.py
pycarmat/GUI/meas/gui/sidebar.py
pycarmat/GUI/meas/gui/tab1.py
pycarmat/GUI/meas/gui/trl_gui.py
pycarmat/GUI/meas/gui/core/__init__.py
pycarmat/GUI/meas/gui/core/_tab.py
pycarmat/GUI/meas/gui/core/_worker.py
pycarmat/GUI/optim/__init__.py
pycarmat/GUI/optim/__main__.py
pycarmat/GUI/optim/gui.py
pycarmat/inverse_model/__init__.py
pycarmat/inverse_model/enhanced_model.py
pycarmat/inverse_model/model.py
pycarmat/inverse_model/tools.py
pycarmat/inverse_model/analyse/__init__.py
pycarmat/inverse_model/analyse/analyze_angle_independence.py
pycarmat/inverse_model/objective_functions/__init__.py
pycarmat/inverse_model/objective_functions/epsilon.py
pycarmat/inverse_model/objective_functions/multi_params.py
pycarmat/inverse_model/score_functions/__init__.py
pycarmat/inverse_model/score_functions/metrics.py
pycarmat/ressources/ESP.py
pycarmat/ressources/__init__.py
pycarmat/ressources/VNA/__init__.py
pycarmat/ressources/VNA/base.py
pycarmat/ressources/VNA/ksVNA.py
pycarmat/ressources/VNA/rsVNA.py
pycarmat/ressources/config/__init__.py
pycarmat/ressources/config/ue31pp_motor.py
pycarmat/ressources/config/ue72pp_motor.py
pycarmat-0.1.0.dev31.dist-info/METADATA
pycarmat-0.1.0.dev31.dist-info/WHEEL
pycarmat-0.1.0.dev31.dist-info/top_level.txt
pycarmat-0.1.0.dev31.dist-info/RECORD
