Metadata-Version: 2.4
Name: pycarmat
Version: 0.1.0.dev31
Summary: Python package for Dielectric Material Characterisation at mmwave bands
Author-email: Gregory Gaudin <gregory.gaudin@imt-atlantique.fr>, Clement Henry <clement.henry@imt-atlantique.fr>
License: AFL-3.0
Classifier: Programming Language :: Python :: 3
Classifier: Operating System :: OS Independent
Requires-Python: >=3.11
Requires-Dist: matplotlib
Requires-Dist: numpy
Requires-Dist: scipy
Requires-Dist: scikit-rf
Requires-Dist: scikit-learn
Requires-Dist: pyvisa
Requires-Dist: pyvisa-py
Requires-Dist: pyserial
Requires-Dist: RsInstrument
Requires-Dist: pyside6
Requires-Dist: qosm
